Workbook
Name Anos_10: Projeto_FII!$A$27
Name Anos_2: Projeto_FII!$A$25
Name Anos_20: Projeto_FII!$A$28
Name Anos_30: Projeto_FII!$A$29
Name Anos_5: Projeto_FII!$A$26
Name Aporte: Projeto_FII!$D$18
Name FII_Desenvolvimento: Projeto_FII!$B$40
Name FII_FOFs: Projeto_FII!$B$39
Name FII_Hibridos: Projeto_FII!$B$38
Name FII_Hotelarias: Projeto_FII!$B$41
Name FII_Papel: Projeto_FII!$B$36
Name FII_Tijolo: Projeto_FII!$B$37
Name Patrimonio: Projeto_FII!$D$21
Name Perfil: Projeto_FII!$D$32
Name qtd_anos: Projeto_FII!$D$19
Name rendimento_carteira: Projeto_FII!$D$14
Name Salario: Projeto_FII!$D$13
Name SegmentaçãodeDados_PERCENTUAL: #N/A
Name Taxa_Mensal: Projeto_FII!$D$20

Sheet Projeto_FII
B12: CONFIGURAÇÕES
B13: Salário | D13: 2000
B14: Rendimento da Carteira | D14: 0.006
B15: Sugestão de Investimento | D15: =Salario*SUBTOTAL(101,Tabela3[PERCENTUAL]) -> 200
B17: INVESTIMENTO MENSAL
B18: Quanto investir por mês? | D18: 200
B19: Por quantos anos investir? | D19: 5
B20: Taxa de rendimento mensal? | D20: 0.01079
B21: Patrimônio acumulado? | D21: =FV(Taxa_Mensal,qtd_anos*12,Aporte*-1) -> 16755.383
B22: Dividendos mensais? | D22: =Patrimonio*rendimento_carteira -> 100.5323
B24: CENÁRIOS | D24: DIVIDENDO
A25: 2 | B25: Quanto em 2 Anos | C25: =FV(Taxa_Mensal,Anos_2*12,Aporte*-1) -> 5445.5255 | D25: =C25*rendimento_carteira -> 32.673153
A26: 5 | B26: Quanto em 5 Anos | C26: =FV(Taxa_Mensal,Anos_5*12,Aporte*-1) -> 16755.383 | D26: =C26*rendimento_carteira -> 100.5323
A27: 10 | B27: Quanto em 10 Anos | C27: =FV(Taxa_Mensal,Anos_10*12,Aporte*-1) -> 48656.843 | D27: =C27*rendimento_carteira -> 291.94106
A28: 20 | B28: Quanto em 20 Anos | C28: =FV(Taxa_Mensal,Anos_20*12,Aporte*-1) -> 225039.68 | D28: =C28*rendimento_carteira -> 1350.2381
A29: 30 | B29: Quanto em 30 Anos | C29: =FV(Taxa_Mensal,Anos_30*12,Aporte*-1) -> 864433.93 | D29: =C29*rendimento_carteira -> 5186.6036
B32: PERFIL | D32: Moderado
B33: VALOR DE INVESTIMENTO MENSAL | D33: =Aporte -> 200
B35: TIPO DE FII | C35: Percentual Sugerido | D35: Valores
B36: PAPEL | C36: =VLOOKUP(Perfil&"-"&FII_Papel,Tbl_Apoio!$A:$D,4,FALSE) -> 0.32 | D36: =C36*$D$33 -> 64
B37: TIJOLO | C37: =VLOOKUP(Perfil&"-"&FII_Tijolo,Tbl_Apoio!$A:$D,4,FALSE) -> 0.35 | D37: =C37*$D$33 -> 70
B38: HÍBRIDOS | C38: =VLOOKUP(Perfil&"-"&FII_Hibridos,Tbl_Apoio!$A:$D,4,FALSE) -> 0.08 | D38: =C38*$D$33 -> 16
B39: FOFs | C39: =VLOOKUP(Perfil&"-"&FII_FOFs,Tbl_Apoio!$A:$D,4,FALSE) -> 0.05 | D39: =C39*$D$33 -> 10
B40: DESENVOLVIMENTO | C40: =VLOOKUP(Perfil&"-"&FII_Desenvolvimento,Tbl_Apoio!$A:$D,4,FALSE) -> 0.1 | D40: =C40*$D$33 -> 20
B41: HOTELARIAS | C41: =VLOOKUP(Perfil&"-"&FII_Hotelarias,Tbl_Apoio!$A:$D,4,FALSE) -> 0.1 | D41: =C41*$D$33 -> 20
B42: Total | D42: =SUM(D36:D41) -> 200

Sheet Tbl_Apoio
G2: %
A3: CHAVE | B3: PERFIL | C3: TIPO DE FII | D3: % | F3: Moderado-TIJOLO | G3: =VLOOKUP(F3,$A:$D,4,FALSE) -> 0.35
A4: =B4&"-"&C4 -> Conservador-PAPEL | B4: Conservador | C4: PAPEL | D4: 0.3
A5: =B5&"-"&C5 -> Conservador-TIJOLO | B5: Conservador | C5: TIJOLO | D5: 0.5
A6: =B6&"-"&C6 -> Conservador-HÍBRIDOS | B6: Conservador | C6: HÍBRIDOS | D6: 0.1
A7: =B7&"-"&C7 -> Conservador-FOFs | B7: Conservador | C7: FOFs | D7: 0.1
A8: =B8&"-"&C8 -> Conservador-DESENVOLVIMENTO | B8: Conservador | C8: DESENVOLVIMENTO | D8: 0
A9: =B9&"-"&C9 -> Conservador-HOTELARIAS | B9: Conservador | C9: HOTELARIAS | D9: 0
A10: =B10&"-"&C10 -> Moderado-PAPEL | B10: Moderado | C10: PAPEL | D10: 0.32
A11: =B11&"-"&C11 -> Moderado-TIJOLO | B11: Moderado | C11: TIJOLO | D11: 0.35
A12: =B12&"-"&C12 -> Moderado-HÍBRIDOS | B12: Moderado | C12: HÍBRIDOS | D12: 0.08
A13: =B13&"-"&C13 -> Moderado-FOFs | B13: Moderado | C13: FOFs | D13: 0.05
A14: =B14&"-"&C14 -> Moderado-DESENVOLVIMENTO | B14: Moderado | C14: DESENVOLVIMENTO | D14: 0.1
A15: =B15&"-"&C15 -> Moderado-HOTELARIAS | B15: Moderado | C15: HOTELARIAS | D15: 0.1
... A21: =B21&"-"&C21 -> Agressivo-HOTELARIAS | B21: Agressivo | C21: HOTELARIAS | D21: 0.1
A23: PERCENTUAL
A24: 0.1
A25: 0.2
A26: 0.3
